eventmagic/__init__.py
eventmagic/exceptions.py
eventmagic/event/__init__.py
eventmagic/schedule/__init__.py
eventmagic-0.2.1.dist-info/METADATA
eventmagic-0.2.1.dist-info/RECORD
eventmagic-0.2.1.dist-info/WHEEL
eventmagic-0.2.1.dist-info/top_level.txt
