Metadata-Version: 2.1
Name: eventmagic
Version: 0.2.1
Summary: Event scheduling with persistence for short-lived processes i.e. AWS Lambda
Home-page: https://github.com/soimafreak/eventmagic
Author: Matthew Smith
License: UNKNOWN
Project-URL: Bug Reports, https://github.com/soimafreak/eventmagic/issues
Project-URL: Source, https://github.com/soimafreak/eventmagic/
Keywords: scheduling events lambda mysql
Platform: UNKNOWN
Classifier: Development Status :: 3 - Alpha
Classifier: Intended Audience :: Developers
Classifier: Topic :: Office/Business :: Scheduling
Classifier: Topic :: Software Development :: Libraries :: Python Modules
Classifier: License :: OSI Approved :: MIT License
Classifier: Programming Language :: Python :: 3.6
Provides-Extra: dev
Requires-Dist: crontab (==0.22.0)
Requires-Dist: mysql-connector-python (==8.0.11)
Provides-Extra: dev
Requires-Dist: flake8; extra == 'dev'
Requires-Dist: flake8-docstrings; extra == 'dev'
Requires-Dist: mock; extra == 'dev'
Requires-Dist: pytest; extra == 'dev'
Requires-Dist: pytest-cov; extra == 'dev'
Requires-Dist: setuptools (>=38.6.0); extra == 'dev'
Requires-Dist: sphinx (==1.5.5); extra == 'dev'
Requires-Dist: twine; extra == 'dev'
Requires-Dist: wheel; extra == 'dev'
